aiopipe/__init__.py
aiopipe-0.2.2.dist-info/LICENSE.txt
aiopipe-0.2.2.dist-info/METADATA
aiopipe-0.2.2.dist-info/WHEEL
aiopipe-0.2.2.dist-info/top_level.txt
aiopipe-0.2.2.dist-info/RECORD
