Metadata-Version: 2.1
Name: aiopipe
Version: 0.2.2
Summary: Multiprocess communication pipes for asyncio
Home-page: https://github.com/kchmck/aiopipe
Author: Mick Koch
Author-email: mick@kochm.co
License: MIT
Project-URL: Documentation, https://kchmck.github.io/aiopipe/aiopipe/
Keywords: async,asyncio,pipe,os.pipe,duplex
Platform: UNKNOWN
Classifier: Development Status :: 4 - Beta
Classifier: Intended Audience :: Developers
Classifier: Operating System :: OS Independent
Classifier: Programming Language :: Python :: 3
Classifier: Programming Language :: Python :: 3 :: Only
Classifier: License :: OSI Approved :: MIT License
Requires-Python: ~=3.7
Provides-Extra: dev
Requires-Dist: tox (~=3.9) ; extra == 'dev'
